unitth/VERSION
unitth/__init__.py
unitth/__main__.py
unitth/core.py
unitth/lib/unitth/unitth.jar
unitth-0.0.14.dist-info/METADATA
unitth-0.0.14.dist-info/RECORD
unitth-0.0.14.dist-info/WHEEL
unitth-0.0.14.dist-info/entry_points.txt
unitth-0.0.14.dist-info/top_level.txt
