Metadata-Version: 2.1
Name: unitth
Version: 0.0.14
Summary: Python interface for UnitTH unit test history report generator
Home-page: https://github.com/KarrLab/unitth
Author: Jonathan Karr
Author-email: jonrkarr@gmail.com
License: MIT
Download-URL: https://github.com/KarrLab/unitth
Keywords: unit test xunit junit unitth HTML history
Platform: UNKNOWN
Classifier: Development Status :: 3 - Alpha
Classifier: Intended Audience :: Developers
Classifier: Topic :: Software Development :: Build Tools
Classifier: License :: OSI Approved :: MIT License
Classifier: Programming Language :: Python
Provides-Extra: tests
Provides-Extra: docs
Provides-Extra: all
Requires-Dist: cement (>=3.0.0)
Requires-Dist: setuptools
Provides-Extra: all
Requires-Dist: junit2html (>=5); extra == 'all'
Requires-Dist: mock; extra == 'all'
Requires-Dist: nose; extra == 'all'
Requires-Dist: nose2unitth; extra == 'all'
Requires-Dist: sphinx (>=1.8); extra == 'all'
Requires-Dist: sphinx-rtd-theme (>=0.4.2); extra == 'all'
Requires-Dist: sphinxcontrib-addmetahtml (>=0.1.1); extra == 'all'
Requires-Dist: sphinxcontrib-bibtex; extra == 'all'
Requires-Dist: sphinxcontrib-googleanalytics (>=0.1.1); extra == 'all'
Requires-Dist: sphinxcontrib-spelling; extra == 'all'
Requires-Dist: sphinxprettysearchresults; extra == 'all'
Provides-Extra: docs
Requires-Dist: sphinx (>=1.8); extra == 'docs'
Requires-Dist: sphinx-rtd-theme (>=0.4.2); extra == 'docs'
Requires-Dist: sphinxcontrib-addmetahtml (>=0.1.1); extra == 'docs'
Requires-Dist: sphinxcontrib-bibtex; extra == 'docs'
Requires-Dist: sphinxcontrib-googleanalytics (>=0.1.1); extra == 'docs'
Requires-Dist: sphinxcontrib-spelling; extra == 'docs'
Requires-Dist: sphinxprettysearchresults; extra == 'docs'
Provides-Extra: tests
Requires-Dist: junit2html (>=5); extra == 'tests'
Requires-Dist: mock; extra == 'tests'
Requires-Dist: nose; extra == 'tests'
Requires-Dist: nose2unitth; extra == 'tests'
